digripy/__init__.py
digripy/digripynetwork.py
digripy/pipe_definitions.json
digripy/run.py
digripy/simulation.py
digripy/tools.py
digripy-0.1.1.dist-info/LICENSE
digripy-0.1.1.dist-info/METADATA
digripy-0.1.1.dist-info/WHEEL
digripy-0.1.1.dist-info/top_level.txt
digripy-0.1.1.dist-info/RECORD
