Metadata-Version: 2.1
Name: digripy
Version: 0.1.1
Summary: District Heating Grid Simulation in Python
Home-page: https://github.com/lvorspel/DiGriPy
Author: Lena Vorspel and Jens Bücker
Author-email: lena.vorspel@ifam.fraunhofer.de
License: UNKNOWN
Project-URL: Bug Tracker, https://github.com/lvorspel/DiGriPy/issues
Platform: UNKNOWN
Classifier: Programming Language :: Python :: 3
Classifier: License :: OSI Approved :: MIT License
Classifier: Operating System :: OS Independent
Classifier: Intended Audience :: Science/Research
Classifier: Topic :: Scientific/Engineering :: Physics
Requires-Python: >=3.6<3.9
Requires-Dist: TESPy (>=0.4.2.post2)
Requires-Dist: openpyxl
Requires-Dist: numpy
Requires-Dist: bokeh
Requires-Dist: pandas
Requires-Dist: jsonref
Requires-Dist: matplotlib
Requires-Dist: decorator
